compression_lib/__init__.py
compression_lib/compression_op.py
compression_lib/compression_op_test.py
compression_lib/compression_op_utils.py
compression_lib/compression_op_utils_test.py
compression_lib/compression_wrapper.py
compression_lib/compression_wrapper_py2.py
compression_lib/compression_wrapper_py2_test.py
compression_lib/compression_wrapper_test.py
compression_lib/decompose_matrix.py
compression_lib/dl_compression_op.py
compression_lib/dl_compression_op_test.py
compression_lib/kmeans_quantize.py
compression_lib/kmeans_quantize_test.py
compression_lib/simhash_compression_op.py
compression_lib/simhash_compression_op_test.py
graph_compression/__init__.py
graph_compression/compression_lib/__init__.py
graph_compression/compression_lib/compression_op.py
graph_compression/compression_lib/compression_op_test.py
graph_compression/compression_lib/compression_op_utils.py
graph_compression/compression_lib/compression_op_utils_test.py
graph_compression/compression_lib/compression_wrapper.py
graph_compression/compression_lib/compression_wrapper_py2.py
graph_compression/compression_lib/compression_wrapper_py2_test.py
graph_compression/compression_lib/compression_wrapper_test.py
graph_compression/compression_lib/decompose_matrix.py
graph_compression/compression_lib/dl_compression_op.py
graph_compression/compression_lib/dl_compression_op_test.py
graph_compression/compression_lib/kmeans_quantize.py
graph_compression/compression_lib/kmeans_quantize_test.py
graph_compression/compression_lib/simhash_compression_op.py
graph_compression/compression_lib/simhash_compression_op_test.py
graph_compression_google_research-0.0.4.dist-info/METADATA
graph_compression_google_research-0.0.4.dist-info/WHEEL
graph_compression_google_research-0.0.4.dist-info/top_level.txt
graph_compression_google_research-0.0.4.dist-info/RECORD
