Metadata-Version: 2.1
Name: graph-compression-google-research
Version: 0.0.4
Summary: Matrix compression for neural networks.
Home-page: UNKNOWN
Author: Google
Author-email: rinap@google.com
License: Apache 2.0
Platform: UNKNOWN
Requires-Python: >=3.6
